autotuner/__init__.py
autotuner/base.py
autotuner/config.py
autotuner/models.py
autotuner/wrappers/__init__.py
autotuner/wrappers/pruner.py
autotuner/wrappers/search.py
autotuner/wrappers/spaces.py
autotuner/wrappers/utils.py
autotuner-0.1.1.dist-info/LICENSE
autotuner-0.1.1.dist-info/METADATA
autotuner-0.1.1.dist-info/WHEEL
autotuner-0.1.1.dist-info/RECORD
