Metadata-Version: 2.1
Name: autotuner
Version: 0.1.1
Summary: Automated hyper-parameter tuning for scikit-learn estimators using optuna.
Home-page: https://github.com/ActurialCapital/autotuner
License: BSD 3-Clause License
Author: ActurialCapital
Requires-Python: >=3.11,<4.0
Classifier: License :: Other/Proprietary License
Classifier: Programming Language :: Python :: 3
Classifier: Programming Language :: Python :: 3.11
Classifier: Programming Language :: Python :: 3.12
Requires-Dist: numpy (>=1.26.4,<2.0.0)
Requires-Dist: optuna (>=3.6.1,<4.0.0)
Requires-Dist: optuna-integration (>=3.6.0,<4.0.0)
Requires-Dist: pandas (>=2.2.2,<3.0.0)
Requires-Dist: scikit-learn (>=1.5.0,<2.0.0)
Project-URL: Repository, https://github.com/ActurialCapital/autotuner
